[
  {
    "title": "星际超级荒诞动画喜剧！《外星小偷里贝》第03话：上岸星球【UP动画】",
    "summary": "两个生活在灰色漂流城“烂柯”的底层星际小偷，老油条西木，带着他的新人搭档——天赋极高却理想主义过头的小偷里贝，在一次次偷取离谱奇物的行动中，被卷入混乱、骗局与社会结构之中。他们身边聚集着前联盟捕手索拉、赏金猎人兄妹、杂货铺老板玛特、玩世不恭的富家女盗贼诺瓦、黑市怪人、等一群古怪搞笑的角色。在“烂柯”与其他人搞笑的日常故事中，他们不断撞上关于社会与人性的荒诞现",
    "url": "https://www.bilibili.com/video/BV1KkEK6CELv",
    "date": "2026-06-14",
    "source": "Bilibili",
    "heat": 80
  },
  {
    "title": "《异环》角色实机战斗丨卡厄斯",
    "summary": "超自然都市开放世界RPG《异环》全新版本「游梦洄廊」现已开启！立刻下载>>>https://www.biligame.com/detail/?id=111795 「情报有误，异象明明在对面那栋楼里。再拖下去就晚了，只能这样了！」 「至于窗玻璃……窗玻璃我会赔的！」",
    "url": "https://www.bilibili.com/video/BV1gdEr6QE1a",
    "date": "2026-06-14",
    "source": "Bilibili",
    "heat": 80
  },
  {
    "title": "「一幕一生」PV公开——从第一幕，走向有你的每一幕。",
    "summary": "从第一幕，走向有你的每一幕。 #恋与深空一幕一生# #恋与深空电影卡# 全新系列五星互动思念「一幕一生」PV公开！  🎞️6月17日更新后~7月2日上午4:59， 猎人可从限定五星思念「沈星回·越夜携心」、「黎深·曙色将倾」、「祁煜·彼日如恒」、「秦彻·别幕终曲」、「夏以昼·触而可及」中任选3张，所选思念许愿概率限时大幅提升，占五星获取几率的75%。 *T",
    "url": "https://www.bilibili.com/video/BV1z5Jc6nEAz",
    "date": "2026-06-14",
    "source": "Bilibili",
    "heat": 80
  },
  {
    "title": "隧夜轮回（莫问来处）第二十一集 情绝人亡 动画 悬疑 微恐怖",
    "summary": "-",
    "url": "https://www.bilibili.com/video/BV17vE56nEtt",
    "date": "2026-06-14",
    "source": "Bilibili",
    "heat": 79
  },
  {
    "title": "Steel Ball Run: JoJo's Bizarre Adventure",
    "summary": "MAL 评分 9.13 | Action · Adventure · Mystery | In the American Old West, the world's greatest race is about to begin. Thousands line up in San Diego to travel over six thousand kilometers for a cha",
    "url": "https://myanimelist.net/anime/61469/Steel_Ball_Run__JoJo_no_Kimyou_na_Bouken",
    "date": "2026-03-19",
    "source": "MyAnimeList",
    "heat": 73
  },
  {
    "title": "Re:ZERO -Starting Life in Another World- Season 4",
    "summary": "MAL 评分 9.04 | Drama · Fantasy · Suspense | In the deadly battle at the Watergate City of Priestella, Subaru and his allies barely emerged victorious—but their triumph came at a great cost. Thro",
    "url": "https://myanimelist.net/anime/61316/Re_Zero_kara_Hajimeru_Isekai_Seikatsu_4th_Season",
    "date": "2026-04-08",
    "source": "MyAnimeList",
    "heat": 72
  },
  {
    "title": "Witch Hat Atelier",
    "summary": "MAL 评分 8.7 | Fantasy | In a world where witches wield breathtaking magic, Coco, coming from a humble background, often wishes she were born one herself. After all, the secre",
    "url": "https://myanimelist.net/anime/51553/Tongari_Boushi_no_Atelier",
    "date": "2026-04-06",
    "source": "MyAnimeList",
    "heat": 69
  },
  {
    "title": "ONE PIECE ⭐87%",
    "summary": " | Action · Adventure · Comedy | Gold Roger was known as the Pirate King, the strongest and most infamous being to have sailed the Grand Line. The capture and death of Roger by the World Government brought a chang",
    "url": "https://anilist.co/anime/21",
    "date": "1999-10-20",
    "source": "AniList",
    "heat": 65
  },
  {
    "title": "Wistoria: Wand and Sword Season 2 ⭐82%",
    "summary": " / 杖と剣のウィストリア Season2 | Action · Adventure · Drama | The second season of Tsue to Tsurugi no Wistoria . Will, a washout student at a magical academy who is unable to use magic, is aiming to join the top tier of mages, the Magia Vande",
    "url": "https://anilist.co/anime/182300",
    "date": "2026-04-12",
    "source": "AniList",
    "heat": 61
  },
  {
    "title": "Daemons of the Shadow Realm ⭐78%",
    "summary": " / 黄泉のツガイ | Action · Adventure · Comedy | In a remote mountain village under the watchful eyes of two stone guardians, the young Yuru contentedly lives off the land while staying close to the only family he has left—Asa, h",
    "url": "https://anilist.co/anime/195600",
    "date": "2026-04-04",
    "source": "AniList",
    "heat": 58
  },
  {
    "title": "雪之少女kanon游玩第一天，咕呜~鲷鱼烧。。。",
    "summary": "",
    "url": "https://www.bilibili.com/video/BV1SFJN6jE2t",
    "date": "2026-06-14",
    "source": "Bilibili",
    "heat": 54
  },
  {
    "title": "即将开播：Mushoku Tensei: Jobless Reincarnation Season 3",
    "summary": " / 無職転生Ⅲ ～異世界行ったら本気だす～ | Adventure · Drama · Ecchi | The third season of Mushoku Tensei: Isekai Ittara Honki Dasu .",
    "url": "https://anilist.co/anime/178789",
    "date": "2026-07-06",
    "source": "AniList",
    "heat": 53
  },
  {
    "title": "【MUGEN】最新V5版SD『Anime stardust』系列整合公开! (下载在简介)",
    "summary": "AUTHOR: Damaylor MUGEN  我用夸克网盘给你分享了「Anime Stardust Ultimate (V5).rar」，点击链接或复制整段内容，打开「夸克网盘APP」即可获取。 /~3db73Z3FWs~:/ 链接：https://pan.quark.cn/s/25f0a438efa5  通过网盘分享的文件：Anime Stardust ",
    "url": "https://www.bilibili.com/video/BV1qfJc6nEgm",
    "date": "2026-06-14",
    "source": "Bilibili",
    "heat": 43
  },
  {
    "title": "即将开播：Saga of Tanya the Evil Season 2",
    "summary": " / 幼女戦記Ⅱ | Action · Fantasy | The second season of Youjo Senki .",
    "url": "https://anilist.co/anime/135865",
    "date": "2026-07-08",
    "source": "AniList",
    "heat": 41
  },
  {
    "title": "Roblox最好的动漫射击游戏来了！",
    "summary": "-",
    "url": "https://www.bilibili.com/video/BV1xWJw6PEjh",
    "date": "2026-06-14",
    "source": "Bilibili",
    "heat": 37
  },
  {
    "title": "【兰斯】人类牧场！纯爱魔王VS渣男npc？兰斯世界观第2集！",
    "summary": "（目前规划了一下，估计得有5集），感谢善人格魔王大大的文案和素材支持！",
    "url": "https://www.bilibili.com/video/BV1VRJP6DET8",
    "date": "2026-06-14",
    "source": "Bilibili",
    "heat": 36
  }
]